jupyter_ai_magics/_version.py
calliope_jupyter_ai_magics-1.1.1.dist-info/METADATA
calliope_jupyter_ai_magics-1.1.1.dist-info/WHEEL
calliope_jupyter_ai_magics-1.1.1.dist-info/licenses/LICENSE
calliope_jupyter_ai_magics-1.1.1.dist-info/RECORD
