Metadata-Version: 2.4
Name: calliope_jupyter_ai_magics
Version: 1.1.1
Dynamic: Keywords
Summary: Jupyter AI magics Python package. Not published on NPM.
Project-URL: Homepage, https://github.com/jupyterlab/jupyter-ai
Project-URL: Bug Tracker, https://github.com/jupyterlab/jupyter-ai/issues
Project-URL: Repository, https://github.com/jupyterlab/jupyter-ai.git
Author-email: Project Jupyter <jupyter@googlegroups.com>
License: BSD 3-Clause License
License-File: LICENSE
Classifier: Framework :: Jupyter
Classifier: License :: OSI Approved :: BSD License
Classifier: Programming Language :: Python
Classifier: Programming Language :: Python :: 3
Classifier: Programming Language :: Python :: 3.9
Classifier: Programming Language :: Python :: 3.10
Classifier: Programming Language :: Python :: 3.11
Classifier: Programming Language :: Python :: 3.12
Requires-Python: >=3.9
Requires-Dist: click<9,>=8.1.0
Requires-Dist: ipython
Requires-Dist: pydantic<3,>=2.10.0
Provides-Extra: all
Requires-Dist: boto3; extra == 'all'
Provides-Extra: dev
Requires-Dist: jupyter-releaser; extra == 'dev'
Requires-Dist: pre-commit<4,>=3.3.3; extra == 'dev'
Requires-Dist: tomlkit; extra == 'dev'
Provides-Extra: test
Requires-Dist: coverage; extra == 'test'
Requires-Dist: pytest; extra == 'test'
Requires-Dist: pytest-asyncio; extra == 'test'
Requires-Dist: pytest-cov; extra == 'test'
